zuds/__init__.py
zuds/alert.py
zuds/archive.py
zuds/bookkeeping.py
zuds/catalog.py
zuds/coadd.py
zuds/constants.py
zuds/core.py
zuds/crossmatch.py
zuds/detections.py
zuds/download.py
zuds/env.py
zuds/external.py
zuds/file.py
zuds/filterobjects.py
zuds/fitsfile.py
zuds/hotpants.py
zuds/image.py
zuds/joins.py
zuds/json_util.py
zuds/mask.py
zuds/model_util.py
zuds/mpi.py
zuds/photometry.py
zuds/plotting.py
zuds/secrets.py
zuds/seeing.py
zuds/send.py
zuds/sextractor.py
zuds/source.py
zuds/spatial.py
zuds/status.py
zuds/subtraction.py
zuds/swarp.py
zuds/thumbnails.py
zuds/utils.py
zuds/astromatic/default.conv
zuds/astromatic/default.nnw
zuds/astromatic/sextractor.conf
zuds/astromatic/sextractor.param
zuds/astromatic/makecoadd/default.swarp
zuds/astromatic/makecoadd/mask.swarp
zuds/astromatic/makesub/default.swarp
zuds/config/default.conf.yaml
zuds/config/test.conf.yaml
zuds-0.1.1.dist-info/LICENSE
zuds-0.1.1.dist-info/METADATA
zuds-0.1.1.dist-info/WHEEL
zuds-0.1.1.dist-info/top_level.txt
zuds-0.1.1.dist-info/RECORD
