Metadata-Version: 2.1
Name: zuds
Version: 0.1.1
Summary: ZTF/ZUDS image processing pipeline
Home-page: https://github.com/zuds-survey/zuds-pipeline
Author: Danny Goldstein & The ZUDS Developers
Author-email: danny@caltech.edu
License: BSD
Platform: UNKNOWN
Requires-Dist: astropy (>=4)
Requires-Dist: fitsio (>=1.0.5)
Requires-Dist: matplotlib (>=3.1.1)
Requires-Dist: numpy (>=1.16.4)
Requires-Dist: pandas (>=0.24.2)
Requires-Dist: penquins (>=1.0.3)
Requires-Dist: photutils (>=0.7.1)
Requires-Dist: psycopg2 (>=2.8.3)
Requires-Dist: PyYAML (>=5.1.1)
Requires-Dist: requests (>=2.22.0)
Requires-Dist: scipy (>=1.3.0)
Requires-Dist: SQLAlchemy (>=1.3.7)
Requires-Dist: ztfquery (>=1.6.2)
Requires-Dist: simplejson
Requires-Dist: pytest (==4.3.1)
Requires-Dist: sncosmo (>=2.1.0)
Requires-Dist: astroquery (>=0.3)
